azure/mgmt/automation/__init__.py
azure/mgmt/automation/automation_client.py
azure/mgmt/automation/version.py
azure/mgmt/automation/models/__init__.py
azure/mgmt/automation/models/activity.py
azure/mgmt/automation/models/activity_output_type.py
azure/mgmt/automation/models/activity_output_type_py3.py
azure/mgmt/automation/models/activity_paged.py
azure/mgmt/automation/models/activity_parameter.py
azure/mgmt/automation/models/activity_parameter_py3.py
azure/mgmt/automation/models/activity_parameter_set.py
azure/mgmt/automation/models/activity_parameter_set_py3.py
azure/mgmt/automation/models/activity_parameter_validation_set.py
azure/mgmt/automation/models/activity_parameter_validation_set_py3.py
azure/mgmt/automation/models/activity_py3.py
azure/mgmt/automation/models/advanced_schedule.py
azure/mgmt/automation/models/advanced_schedule_monthly_occurrence.py
azure/mgmt/automation/models/advanced_schedule_monthly_occurrence_py3.py
azure/mgmt/automation/models/advanced_schedule_py3.py
azure/mgmt/automation/models/agent_registration.py
azure/mgmt/automation/models/agent_registration_keys.py
azure/mgmt/automation/models/agent_registration_keys_py3.py
azure/mgmt/automation/models/agent_registration_py3.py
azure/mgmt/automation/models/agent_registration_regenerate_key_parameter.py
azure/mgmt/automation/models/agent_registration_regenerate_key_parameter_py3.py
azure/mgmt/automation/models/automation_account.py
azure/mgmt/automation/models/automation_account_create_or_update_parameters.py
azure/mgmt/automation/models/automation_account_create_or_update_parameters_py3.py
azure/mgmt/automation/models/automation_account_paged.py
azure/mgmt/automation/models/automation_account_py3.py
azure/mgmt/automation/models/automation_account_update_parameters.py
azure/mgmt/automation/models/automation_account_update_parameters_py3.py
azure/mgmt/automation/models/automation_client_enums.py
azure/mgmt/automation/models/azure_query_properties.py
azure_mgmt_automation-0.1.1.dist-info/METADATA
azure_mgmt_automation-0.1.1.dist-info/WHEEL
azure_mgmt_automation-0.1.1.dist-info/top_level.txt
azure_mgmt_automation-0.1.1.dist-info/RECORD
